pydantic_autotag/__init__.py
pydantic_autotag/py.typed
pydantic_autotag-0.1.0.dist-info/WHEEL
pydantic_autotag-0.1.0.dist-info/METADATA
pydantic_autotag-0.1.0.dist-info/RECORD
