Metadata-Version: 2.3
Name: pydantic-autotag
Version: 0.1.0
Summary: Create Pydantic tagged unions without the boilerplate
Author: Eitan Mosenkis
Author-email: Eitan Mosenkis <eitan@levro.com>
Requires-Dist: pydantic>=2
Requires-Python: >=3.10
